imaps/__about__.py
imaps/__init__.py
imaps/base/__init__.py
imaps/base/exceptions.py
imaps/base/operation.py
imaps/base/sheet.py
imaps/base/site.py
imaps/base/validation.py
imaps/base/constants/__init__.py
imaps/base/constants/assets.py
imaps/base/constants/sheet.py
imaps/operations/__init__.py
imaps/operations/example.py
imaps/operations/sites.py
imaps/sandbox/__init__.py
imaps/sandbox/kmers.py
imaps/scripts/__init__.py
imaps/scripts/batch_download.py
imaps/scripts/check_assets.py
imaps-0.5.2.dist-info/LICENSE
imaps-0.5.2.dist-info/METADATA
imaps-0.5.2.dist-info/WHEEL
imaps-0.5.2.dist-info/entry_points.txt
imaps-0.5.2.dist-info/top_level.txt
imaps-0.5.2.dist-info/RECORD
